decipher/__init__.py
decipher/plot/__init__.py
decipher/plot/basis_decomposition.py
decipher/plot/decipher.py
decipher/plot/trajectory_inference.py
decipher/plot/utils.py
decipher/tools/__init__.py
decipher/tools/_basis_decomposition/__init__.py
decipher/tools/_basis_decomposition/inference.py
decipher/tools/_basis_decomposition/model.py
decipher/tools/_basis_decomposition/run.py
decipher/tools/_decipher/__init__.py
decipher/tools/_decipher/data.py
decipher/tools/_decipher/decipher.py
decipher/tools/_decipher/module.py
decipher/tools/basis_decomposition.py
decipher/tools/decipher.py
decipher/tools/trajectory_inference.py
decipher/tools/utils.py
decipher/utils.py
scdecipher-0.1.2.dist-info/METADATA
scdecipher-0.1.2.dist-info/WHEEL
scdecipher-0.1.2.dist-info/RECORD
